tested/__init__.py
tested/multiple.py
tested-0.0.2.dist-info/LICENSE
tested-0.0.2.dist-info/METADATA
tested-0.0.2.dist-info/WHEEL
tested-0.0.2.dist-info/top_level.txt
tested-0.0.2.dist-info/RECORD
