Metadata-Version: 2.1
Name: tested
Version: 0.0.2
Summary: Python test utils
Home-page: https://github.com/i2mint/tested
Author: OtoSense
License: apache-2.0
Platform: any
